Workbook

Sheet Dashboard
B1: Dashboard
A2: Period:
A4: Area | B4: Total Tasks | C4: Completed Tasks | D4: % Complete | E4: Last Completion Date
A5: Governance | B5: 15 | C5: =+COUNTIF(Governance!$K$3:$K$18,"Completed") -> 0 | D5: =+C5/B5 -> 0
A6: Finance | B6: 13 | C6: =+COUNTIF(Finance!$K$3:$K$15,"Completed") -> 0 | D6: =+C6/B6 -> 0
A7: Fundraising | B7: 7 | C7: =+COUNTIF(Fundraising!$K$3:$K$9,"Completed") -> 0 | D7: =+C7/B7 -> 0
A8: Programs | B8: 6 | C8: =+COUNTIF(Programs!$K$3:$K$8,"Completed") -> 0 | D8: =+C8/B8 -> 0
A9: HR and Volunteers | B9: 5 | C9: =+COUNTIF('HR and Volunteers'!$K$3:$K$7,"Completed") -> 0 | D9: =+C9/B9 -> 0
A10: Risk and Compliance | B10: 6 | C10: =+COUNTIF('Risk and Compliance'!$K$3:$K$8,"Completed") -> 0 | D10: =+C10/B10 -> 0
A11: Communications and Reporting | B11: 5 | C11: =+COUNTIF('Communications and Reporting'!$K$3:$K$7,"Completed") -> 0 | D11: =+C11/B11 -> 0

Sheet Summary
B1: Monthly Charity Compliance - Summary
A2: Period:
A4: Area | B4: Total Tasks | C4: Completed Tasks | D4: % Complete | E4: Outstanding Tasks (Top 5)
A5: Governance | B5: 15 | C5: =+COUNTIF(Governance!$K$3:$K$18,"Completed") -> 0 | D5: =+C5/B5 -> 0 | E5: Monthly Board Meeting (or delegation); Minutes and Resolutions; Responsible Persons Register; Fit & Proper Person & Conflicts Checks; Conflict of Interest Register Review
A6: Finance | B6: 13 | C6: =+COUNTIF(Finance!$K$3:$K$15,"Completed") -> 0 | D6: =+C6/B6 -> 0 | E6: Bank Reconciliations - All Accounts; Donation & Fund Reconciliation; Management Accounts & Variance Analysis; Payroll & STP Reporting; BAS / GST Review
A7: Fundraising | B7: 7 | C7: =+COUNTIF(Fundraising!$K$3:$K$9,"Completed") -> 0 | D7: =+C7/B7 -> 0 | E7: Donation Receipts: Compliance Check; Donation Allocation & Restrictions; Appeals & Campaign Compliance; Fundraising Licence & State Compliance; Major Donor & Sponsorship Agreements
A8: Programs | B8: 6 | C8: =+COUNTIF(Programs!$K$3:$K$8,"Completed") -> 0 | D8: =+C8/B8 -> 0 | E8: Program KPI & Output Review; Beneficiary Records & Privacy; Safeguarding & WWCC Checks; Client Feedback & Complaints; Program Budget & Expenditure Tracking
A9: HR_and_Volunteers | B9: 5 | C9: =+COUNTIF('HR and Volunteers'!$K$3:$K$7,"Completed") -> 0 | D9: =+C9/B9 -> 0 | E9: Payroll & Contractor Classification Review; Mandatory Training & Licences; Background Checks & WWCC; Volunteer Agreements & Insurance; Performance & Wellbeing Check-ins
A10: Risk_and_Compliance | B10: 6 | C10: =+COUNTIF('Risk and Compliance'!$K$3:$K$8,"Completed") -> 0 | D10: =+C10/B10 -> 0 | E10: Risk Register Review & Top Risks; WHS Inspection & Hazard Log; Incident Management & Reporting; Cybersecurity & Access Review; Data Breach Readiness & NDB Assessment
A11: Communications_and_Reporting | B11: 5 | C11: =+COUNTIF('Communications and Reporting'!$K$3:$K$7,"Completed") -> 0 | D11: =+C11/B11 -> 0 | E11: Website & Charity Register Public Info; Annual Information Statement Readiness; Donor & Stakeholder Communications; Media & Reputation Monitoring; External Reporting & Grant Requirements
A13: Sign off:
A15: Date:
A17: Position:

Sheet Governance
C1: Governance Checklist
A2: Task ID | B2: Task | C2: Description | D2: Reference | E2: Responsible Person | F2: Frequency | G2: Evidence Required | H2: Completed (Y/N) | I2: Date Completed | J2: Comments | K2: Status | L2: Sign-off Name
A3: GOV-01 | B3: Monthly Board Meeting (or delegation) | C3: Confirm meeting scheduled; prepare and distribute agenda and papers at least 7 days prior; confirm quorum and record attendance. | D3: ACNC Governance Standards; Constitution; Corporations Act | E3: Company Secretary / Chair / CEO | F3: Monthly | G3: Agenda, meeting pack distribution log, minutes, attendance sheet | K3: Not started
A4: GOV-02 | B4: Minutes and Resolutions | C4: Circulate draft minutes within 7 business days; record resolutions, action items, responsible persons and deadlines; file approved minutes in minute book. | D4: Corporations Act; ACNC record-keeping guidance | E4: Company Secretary | F4: Monthly | G4: Draft & approved minutes, resolution register | K4: Not started
A5: GOV-03 | B5: Responsible Persons Register | C5: Review current Responsible People; confirm consents, contact details and roles; update ACNC Charity Portal within statutory timeframe (28 days for medium/large charities). | D5: ACNC Notifying changes guidance; ACNC forms | E5: Company Secretary / Governance Officer | F5: Monthly (check for changes) | G5: Updated register, ACNC portal confirmation if updated | K5: Not started
A6: GOV-04 | B6: Fit & Proper Person & Conflicts Checks | C6: Ensure newly appointed Responsible People have completed: consent to act, declaration of disqualifying histories (bankruptcy, criminal convictions), conflicts of interest and probity checks. | D6: Corporations Act; ACNC Governance Standards | E6: Governance Officer / Chair | F6: As required; verify monthly for new entries | G6: Signed consents, disclosure forms, probity check records | K6: Not started
A7: GOV-05 | B7: Conflict of Interest Register Review | C7: Review register; ensure declarations recorded in minutes; update mitigation plans for any declared conflicts. | D7: ACNC Governance Standards | E7: Chair / Company Secretary | F7: Monthly | G7: Conflict register, minutes referring to declarations | K7: Not started
A8: GOV-06 | B8: Board Skills Matrix & Succession | C8: Update skills matrix; identify gaps; report on upcoming vacancies and succession plan actions. | D8: Good governance practice; ACNC guidance | E8: Chair / Governance Committee | F8: Quarterly (review monthly status) | G8: Skills matrix, succession plan
A9: GOV-07 | B9: Delegations & Authorisations | C9: Review delegated authorities and any approvals given under delegation during the month (finance, contracts, HR). | D9: Constitution; Delegations Policy | E9: CEO / CFO / Company Secretary | F9: Monthly | G9: Delegation register, approval records
A10: GOV-08 | B10: Policy Review Cycle | C10: Confirm policies reviewed per schedule (whistleblower, privacy, fraud, fundraising, safeguarding, procurement). Update any overdue policies. | D10: ACNC Governance Standards; internal policy schedule | E10: Governance Officer / Head of HR | F10: Monthly (by schedule) | G10: Policy register, updated policy docs, endorsement records
A11: GOV-09 | B11: Whistleblower & Complaints | C11: Review whistleblower and complaints logs; ensure appropriate handling, protections and follow-ups; escalate to board if required. | D11: Whistleblower protections Act; ACNC complaints guidance | E11: Company Secretary / Risk Officer | F11: Monthly | G11: Complaints & whistleblower log, outcomes, corrective action
A12: GOV-10 | B12: Related Party Transactions | C12: Identify and review any related-party transactions; ensure they were approved per policy and recorded. | D12: ACNC Guidance; Corporations Act | E12: CFO / Governance Officer | F12: Monthly | G12: Related-party register, approvals, supporting docs
A13: GOV-11 | B13: Board Training & Induction | C13: Confirm induction for new Responsible People and ongoing training completed (governance, ACNC obligations, DGR rules, child safety as applicable). | D13: ACNC checklist for new responsible people | E13: Governance Officer / Company Secretary | F13: Monthly (training schedule) | G13: Training records, induction packs
A14: GOV-12 | B14: Confidentiality & Privacy Compliance | C14: Ensure board & staff have signed confidentiality agreements where required and privacy training up to date. | D14: Privacy Act; ACNC governance standards | E14: Privacy Officer / Company Secretary | F14: Monthly (by schedule) | G14: Signed agreements, training logs
A15: GOV-13 | B15: Insurance & D&O | C15: Verify insurance policies active (D&O, public liability, volunteer cover); confirm upcoming renewals and claims status. | D15: Insurance policies; risk controls | E15: Risk & CFO | F15: Monthly | G15: Insurance register, current certificates
A16: GOV-14 | B16: Governance Reporting Pack | C16: Prepare standard monthly governance pack for board including risk register, finance snapshot, major incidents and compliance exceptions. | D16: ACNC reporting expectations | E16: CEO / Company Secretary | F16: Monthly | G16: Board pack distribution log
A17: GOV-15 | B17: Regulatory Notifications & Compliance Calendar | C17: Review upcoming lodgements (ACNC AIS, ASIC annual statement, BAS, grant reports) and ensure deadlines are on schedule. | D17: ACNC, ASIC, ATO guidance | E17: Company Secretary / CFO | F17: Monthly | G17: Compliance calendar, lodgement evidence

Sheet Finance
B1: Finance Checklist
A2: Task ID | B2: Task | C2: Description | D2: Reference | E2: Responsible Person | F2: Frequency | G2: Evidence Required | H2: Completed (Y/N) | I2: Date Completed | J2: Comments | K2: Status | L2: Sign-off Name
A3: FIN-01 | B3: Bank Reconciliations - All Accounts | C3: Reconcile each bank account, merchant accounts and payment gateways to GL; review and clear reconciling items. | D3: ASIC guidance on financial reporting; internal control | E3: Finance Manager / Accountant | F3: Monthly | G3: Bank reconciliation reports, sign-off | K3: Not started
A4: FIN-02 | B4: Donation & Fund Reconciliation | C4: Reconcile donations per campaign/platform (online, EFT, cash, events) to bank & donation ledger; flag unallocated or restricted gifts. | D4: ATO DGR receipts guidance; internal donations policy | E4: Fundraising Manager / Accountant | F4: Monthly | G4: Donation ledger, reconciliation worksheet
A5: FIN-03 | B5: Management Accounts & Variance Analysis | C5: Produce P&L, Balance Sheet, Cash Flow, and a variance analysis with explanations for variances >5% or material items. | D5: ACNC financial reporting guidance; accounting standards | E5: CFO / Finance Manager | F5: Monthly | G5: Management accounts, variance commentary
A6: FIN-04 | B6: Payroll & STP Reporting | C6: Confirm payroll processed, Single Touch Payroll lodged, superannuation paid, tax withheld accurate and payroll reconciliations complete. | D6: ATO STP guidance; Fair Work Act | E6: Payroll Manager / HR | F6: Monthly (per pay run) | G6: Payroll registers, STP receipts, super statements
A7: FIN-05 | B7: BAS / GST Review | C7: Reconcile GST collected and paid; prepare BAS estimates/working papers and flag any adjustments. | D7: ATO BAS guidance | E7: Accountant / CFO | F7: Monthly (if lodged monthly/quarterly) | G7: BAS working papers, supporting invoices
A8: FIN-06 | B8: Accounts Payable & Authorisations | C8: Confirm AP aged report reviewed, payments approved per delegations, check for duplicate payments and unusual vendors. | D8: Delegations policy, procurement policy | E8: Accounts Payable Officer / Finance Manager | F8: Weekly/Monthly | G8: AP aged report, payment approvals
A9: FIN-07 | B9: Accounts Receivable & Grants Income | C9: Review AR aging, follow-up debts; reconcile grant income to grant agreements and deferred income schedules. | D9: Grant agreements; ACNC reporting | E9: Grants Officer / Accountant | F9: Monthly | G9: AR aged, grant ledger, acquittal tracker
A10: FIN-08 | B10: Expense & Fraud Review | C10: Run exception reports for unusual transactions, merchant codes, or high-value purchases; review expense reimbursements. | D10: Internal control, fraud policy | E10: Finance Manager / Internal Audit | F10: Monthly | G10: Exception reports, investigation logs
A11: FIN-09 | B11: Fixed Assets & Depreciation | C11: Update asset register for new purchases/disposals; reconcile ledger and calculate monthly depreciation. | D11: Accounting standards; asset policy | E11: Finance Officer | F11: Monthly | G11: Asset register, capex approvals
A12: FIN-10 | B12: Related Party & Trustee Transactions | C12: Ensure related party transactions have approvals and are disclosed where required. | D12: ACNC/Corporations Act disclosure requirements | E12: CFO / Company Secretary | F12: Monthly | G12: Related party register, disclosures
A13: FIN-11 | B13: Budget Monitoring & Cash Forecast | C13: Update cashflow forecast, highlight upcoming funding shortfalls or surplus and recommend actions. | D13: Board-approved budget; ACNC guidance | E13: CFO | F13: Monthly | G13: Cashflow forecast, management commentary
A14: FIN-12 | B14: Grant & Contract Compliance | C14: Match expenditure to grant budget lines, check procurement compliance, prepare accruals and ensure milestone evidence is retained. | D14: Grant agreements; funder requirements | E14: Grants Officer / Program Manager | F14: Monthly | G14: Grant files, milestone evidence
A15: FIN-13 | B15: Audit Preparedness & Working Papers | C15: Maintain working papers for auditors, update audit issue log, and ensure timely responses to auditor requests. | D15: Audit standards; ASIC guidance | E15: Finance Manager / Audit Committee | F15: Monthly | G15: Working papers index, audit log

Sheet Fundraising
B1: Fundraising Checklist
A2: Task ID | B2: Task | C2: Description | D2: Reference | E2: Responsible Person | F2: Frequency | G2: Evidence Required | H2: Completed (Y/N) | I2: Date Completed | J2: Comments | K2: Status | L2: Sign-off Name
A3: FUND-01 | B3: Donation Receipts: Compliance Check | C3: Issue receipts that meet ATO DGR requirements (include org name/ABN, date, amount, statement that the gift is deductible, description of any benefit), and keep copies. | D3: ATO Receipts guidance (DGR requirements). | E3: Fundraising Manager / Finance | F3: Within 7 days of gift | G3: Sample receipts, receipt log
A4: FUND-02 | B4: Donation Allocation & Restrictions | C4: Track restricted or purpose-specific donations; maintain a restricted funds ledger and evidence donor conditions are honoured. | D4: DGR rules; grant conditions | E4: Fundraising Manager / Grants Officer | F4: Monthly | G4: Restricted funds ledger, donor communication
A5: FUND-03 | B5: Appeals & Campaign Compliance | C5: Review active appeals content for accuracy, ensure funds to be used as stated and monitor campaign performance. | D5: ACNC fundraising guidance; ATO DGR | E5: Fundraising Team / Communications | F5: Monthly | G5: Campaign briefs, performance report
A6: FUND-04 | B6: Fundraising Licence & State Compliance | C6: Check fundraising licences and permits in states/territories for events/appeals and renew as required; maintain register. | D6: State fundraising regulators; ACNC guidance | E6: Compliance Officer / Fundraising Manager | F6: Monthly (by schedule) | G6: Licence register, permits
A7: FUND-05 | B7: Major Donor & Sponsorship Agreements | C7: Ensure agreements are documented, record any naming rights or conditionality, and confirm sponsor benefits delivered. | D7: Contract law; donor agreements | E7: Fundraising Manager / CEO | F7: Monthly | G7: Signed agreements, sponsorship fulfilment log
A8: FUND-06 | B8: Crowdfunding & Third-Party Platforms | C8: Reconcile funds raised via third-party platforms; confirm platform T&Cs and donor receipting are compliant. | D8: Platform terms; ATO DGR receipting | E8: Fundraising / Finance | F8: Monthly (campaign close) | G8: Platform reconciliations, terms
A9: FUND-07 | B9: Gift Acceptance & Refusal Log | C9: Operate per Gift Acceptance Policy; record any refused gifts and rationale (e.g., restricted, anti-social conditions). | D9: Gift Acceptance Policy; DGR rules | E9: Fundraising Manager / CEO | F9: Monthly | G9: Gift log

Sheet Programs
B1: Programs Checklist
A2: Task ID | B2: Task | C2: Description | D2: Reference | E2: Responsible Person | F2: Frequency | G2: Evidence Required | H2: Completed (Y/N) | I2: Date Completed | J2: Comments | K2: Status | L2: Sign-off Name
A3: PROG-01 | B3: Program KPI & Output Review | C3: Collect KPI data (outputs, beneficiaries served) and compare against monthly targets; highlight shortfalls and corrective actions. | D3: Grant agreements; ACNC AIS programs section | E3: Program Managers / M&E Officer | F3: Monthly | G3: KPI dashboard, M&E reports
A4: PROG-02 | B4: Beneficiary Records & Privacy | C4: Ensure beneficiary records are current, consent recorded, and data stored per privacy policy; purge outdated data as required. | D4: Privacy Act; ACNC governance standards | E4: Program Manager / Privacy Officer | F4: Monthly | G4: Beneficiary registers, consent forms
A5: PROG-03 | B5: Safeguarding & WWCC Checks | C5: Verify staff and volunteer WWCC/work with vulnerable people checks up to date and completed; ensure safeguarding training completed. | D5: State child safety laws; ACNC guidance | E5: Program Director / HR | F5: Monthly | G5: WWCC register, training records
A6: PROG-04 | B6: Client Feedback & Complaints | C6: Review service user feedback, complaints and outcomes; implement corrective actions and improvements. | D6: ACNC governance standards; complaints policy | E6: Quality Manager / Program Manager | F6: Monthly | G6: Feedback logs, complaints register
A7: PROG-05 | B7: Program Budget & Expenditure Tracking | C7: Confirm program expenditure aligns to budgets and grant conditions; code transactions correctly. | D7: Grant agreements; finance controls | E7: Program Manager / Finance | F7: Monthly | G7: Program ledger, variance reports
A8: PROG-06 | B8: Partnership & Sub-grant Oversight | C8: Review partner performance, ensure MOUs and sub-grant documentation are up-to-date and funds used appropriately. | D8: ACNC External Conduct Standards (if overseas); grant rules | E8: Program Manager / Grants Officer | F8: Monthly | G8: Partner reports, MOU register

Sheet HR and Volunteers
B1: HR and Volunteers Checklist
A2: Task ID | B2: Task | C2: Description | D2: Reference | E2: Responsible Person | F2: Frequency | G2: Evidence Required | H2: Completed (Y/N) | I2: Date Completed | J2: Comments | K2: Status | L2: Sign-off Name
A3: HR-01 | B3: Payroll & Contractor Classification Review | C3: Spot-check contractor vs employee classification; ensure correct PAYG withholding and super for employees. | D3: Fair Work Act; ATO guidance | E3: HR Manager / Payroll | F3: Monthly | G3: Contractor files, payroll reports
A4: HR-02 | B4: Mandatory Training & Licences | C4: Track completion of mandatory training (WHS, safeguarding, privacy) and professional registrations. | D4: WHS legislation; ACNC governance standards | E4: HR Manager / Training Coordinator | F4: Monthly | G4: Training matrix, certificates
A5: HR-03 | B5: Background Checks & WWCC | C5: Verify criminal history and WWCC checks for staff & volunteers working with vulnerable groups are current. | D5: State screening laws; ACNC guidance | E5: Volunteer Coordinator / HR | F5: Monthly | G5: Screening register
A6: HR-04 | B6: Volunteer Agreements & Insurance | C6: Ensure volunteer agreements are signed, roles defined and covered by volunteer insurance. | D6: Insurance policy; volunteer policy | E6: Volunteer Coordinator | F6: Monthly | G6: Volunteer register, signed agreements
A7: HR-05 | B7: Performance & Wellbeing Check-ins | C7: Managers complete short monthly wellbeing check-ins; track significant HR issues for escalation. | D7: Workplace health guidance | E7: Line Managers / HR | F7: Monthly | G7: Check-in notes, HR case log

Sheet Risk and Compliance
B1: Risk and Compliance Checklist
A2: Task ID | B2: Task | C2: Description | D2: Reference | E2: Responsible Person | F2: Frequency | G2: Evidence Required | H2: Completed (Y/N) | I2: Date Completed | J2: Comments | K2: Status | L2: Sign-off Name
A3: RISK-01 | B3: Risk Register Review & Top Risks | C3: Update risk register, reassess controls and residual ratings for top 10 risks; verify mitigation actions underway. | D3: ACNC Governance Standards; internal risk policy | E3: Risk & Compliance Officer / Executive | F3: Monthly | G3: Updated risk register, action tracker | K3: Not started
A4: RISK-02 | B4: WHS Inspection & Hazard Log | C4: Conduct site inspections, update hazard log and confirm corrective actions closed or scheduled. | D4: WHS legislation | E4: WHS Officer / Facilities | F4: Monthly | G4: Inspection checklist, hazard log | K4: Not started
A5: RISK-03 | B5: Incident Management & Reporting | C5: Review incidents (safety, financial, reputational); confirm investigations, corrective actions and reports to insurers/board as required. | D5: Insurance conditions; ACNC incident guidance | E5: Risk Officer / Program Manager | F5: Monthly | G5: Incident register, investigation reports | K5: Not started
A6: RISK-04 | B6: Cybersecurity & Access Review | C6: Review user accounts, privileged access, MFA compliance, backups tested and incident response readiness; patching status. | D6: OAIC guidance; Cybersecurity frameworks | E6: IT Manager / Security Officer | F6: Monthly | G6: Access logs, backup test evidence, vulnerability scan summary | K6: Not started
A7: RISK-05 | B7: Data Breach Readiness & NDB Assessment | C7: Confirm data breach response plan in place and test; assess any suspected breaches against NDB criteria and notify OAIC/affected individuals if required. | D7: OAIC NDB scheme guidance | E7: Privacy Officer / IT Manager | F7: Monthly (or after any incident) | G7: Breach response plan, assessment notes, notifications if any | K7: Not started
A8: RISK-06 | B8: Insurance Policy Review | C8: Ensure policies in force, claims recorded and renewal premiums budgeted. | D8: Insurance contracts; risk policy | E8: CFO / Risk Officer | F8: Monthly | G8: Insurance register, certificates | K8: Not started

Sheet Communications and Reporting
B1: Communications and Reporting Checklist
A2: Task ID | B2: Task | C2: Description | D2: Reference | E2: Responsible Person | F2: Frequency | G2: Evidence Required | H2: Completed (Y/N) | I2: Date Completed | J2: Comments | K2: Status | L2: Sign-off Name
A3: COMMS-01 | B3: Website & Charity Register Public Info | C3: Ensure ACNC Charity Register public information and website pages reflect correct charitable purpose, fundraising, contact details and governance statements. | D3: ACNC public disclosure guidance | E3: Communications Manager / Company Secretary | F3: Monthly | G3: Website screenshots, ACNC register check
A4: COMMS-02 | B4: Annual Information Statement Readiness | C4: Maintain required records for AIS (program descriptions, revenue figures, related parties, overseas activities) so that the AIS can be completed accurately when due. | D4: ACNC Annual Information Statement guidance | E4: Company Secretary / Finance / Programs | F4: Monthly | G4: AIS working file, program evidence
A5: COMMS-03 | B5: Donor & Stakeholder Communications | C5: Prepare monthly donor update, publish impact stories only where consistent with consent and privacy; track opt-outs. | D5: Privacy Act; donor communication policy | E5: Fundraising / Communications | F5: Monthly | G5: Mailing lists, campaign reports
A6: COMMS-04 | B6: Media & Reputation Monitoring | C6: Monitor media/social media for mentions or issues; escalate reputational issues to Exec & Board. | D6: ACNC charity standards (reputational risk) | E6: Communications Manager | F6: Daily/Monthly summary | G6: Media log, escalation records
A7: COMMS-05 | B7: External Reporting & Grant Requirements | C7: Track upcoming grant reporting deadlines and ensure deliverables/metrics are collated monthly. | D7: Grant agreements; funder conditions | E7: Grants Officer / Program Manager | F7: Monthly | G7: Reporting schedule, draft reports
